{
  "annotations": {
    "changelogDate": "20240725093214"
  },
  "applications": "*",
  "clientRootFolder": "HopDong",
  "databaseType": "sql",
  "dto": "mapstruct",
  "fields": [
    {
      "fieldName": "idLoaiHopDong",
      "fieldType": "Long"
    },
    {
      "fieldName": "idDonVi",
      "fieldType": "Long"
    },
    {
      "fieldName": "chieuDai",
      "fieldType": "Long"
    },
    {
      "fieldName": "tienTo",
      "fieldType": "String"
    },
    {
      "fieldName": "phuongThucThanhToan",
      "fieldType": "String"
    },
    {
      "fieldName": "thongTinThem",
      "fieldType": "String"
    },
    {
      "fieldName": "giaTri",
      "fieldType": "Long"
    },
    {
      "fieldName": "hienThi",
      "fieldType": "String"
    },
    {
      "fieldName": "trangThai",
      "fieldType": "Long"
    }
  ],
  "microserviceName": "HopDong",
  "name": "CauHinhHopDong",
  "pagination": "pagination",
  "relationships": [],
  "searchEngine": "no",
  "service": "serviceClass"
}
